cliqz/__init__.py
cliqz/__version__.py
cliqz/bcolors.py
cliqz/configuration.py
cliqz/main.py
cliqz/question.py
cliqz/quiz.py
cliqz-0.1.4.dist-info/LICENSE
cliqz-0.1.4.dist-info/METADATA
cliqz-0.1.4.dist-info/WHEEL
cliqz-0.1.4.dist-info/dependency_links.txt
cliqz-0.1.4.dist-info/entry_points.txt
cliqz-0.1.4.dist-info/top_level.txt
cliqz-0.1.4.dist-info/RECORD
