Metadata-Version: 2.1
Name: cliqz
Version: 0.1.4
Summary: A simple commandline app for quizes
Home-page: https://github.com/InTEGr8or/cliqz
Author: Mark Stouffer
Author-email: mark.stouffer@verys.com
License: MIT
Download-URL: https://github.com/InTEGr8or/cliqz/archive/master.zip
Platform: UNKNOWN
Classifier: License :: OSI Approved :: MIT License
Classifier: Programming Language :: Python :: 2.7
Classifier: Programming Language :: Python :: 3
Classifier: Programming Language :: Python :: 3.7
Requires-Python: >=2.7
Requires-Dist: click
Requires-Dist: pyyaml
Requires-Dist: pytest
